{
  "schedules": [
    {
      "week": 1,
      "matchups": [
        {
          "week": 1,
          "leagueId": "league-beltway",
          "homeTeamId": "league-beltway-team-1",
          "awayTeamId": "league-beltway-team-4",
          "homeScore": 0,
          "awayScore": 0,
          "completed": true
        },
        {
          "week": 1,
          "leagueId": "league-beltway",
          "homeTeamId": "league-beltway-team-2",
          "awayTeamId": "league-beltway-team-3",
          "homeScore": 0,
          "awayScore": 0,
          "completed": true
        },
        {
          "week": 1,
          "leagueId": "league-capitol",
          "homeTeamId": "league-capitol-team-1",
          "awayTeamId": "league-capitol-team-4",
          "homeScore": 0,
          "awayScore": 0,
          "completed": true
        },
        {
          "week": 1,
          "leagueId": "league-capitol",
          "homeTeamId": "league-capitol-team-2",
          "awayTeamId": "league-capitol-team-3",
          "homeScore": 0,
          "awayScore": 0,
          "completed": true
        },
        {
          "week": 1,
          "leagueId": "league-swamp",
          "homeTeamId": "league-swamp-team-1",
          "awayTeamId": "league-swamp-team-4",
          "homeScore": 0,
          "awayScore": 0,
          "completed": true
        },
        {
          "week": 1,
          "leagueId": "league-swamp",
          "homeTeamId": "league-swamp-team-2",
          "awayTeamId": "league-swamp-team-3",
          "homeScore": 0,
          "awayScore": 0,
          "completed": true
        }
      ]
    },
    {
      "week": 2,
      "matchups": [
        {
          "week": 2,
          "leagueId": "league-beltway",
          "homeTeamId": "league-beltway-team-1",
          "awayTeamId": "league-beltway-team-2",
          "homeScore": 0,
          "awayScore": 0,
          "completed": true
        },
        {
          "week": 2,
          "leagueId": "league-beltway",
          "homeTeamId": "league-beltway-team-3",
          "awayTeamId": "league-beltway-team-4",
          "homeScore": 0,
          "awayScore": 0,
          "completed": true
        },
        {
          "week": 2,
          "leagueId": "league-capitol",
          "homeTeamId": "league-capitol-team-1",
          "awayTeamId": "league-capitol-team-2",
          "homeScore": 0,
          "awayScore": 0,
          "completed": true
        },
        {
          "week": 2,
          "leagueId": "league-capitol",
          "homeTeamId": "league-capitol-team-3",
          "awayTeamId": "league-capitol-team-4",
          "homeScore": 0,
          "awayScore": 0,
          "completed": true
        },
        {
          "week": 2,
          "leagueId": "league-swamp",
          "homeTeamId": "league-swamp-team-1",
          "awayTeamId": "league-swamp-team-2",
          "homeScore": 0,
          "awayScore": 0,
          "completed": true
        },
        {
          "week": 2,
          "leagueId": "league-swamp",
          "homeTeamId": "league-swamp-team-3",
          "awayTeamId": "league-swamp-team-4",
          "homeScore": 0,
          "awayScore": 0,
          "completed": true
        }
      ]
    },
    {
      "week": 3,
      "matchups": [
        {
          "week": 3,
          "leagueId": "league-beltway",
          "homeTeamId": "league-beltway-team-1",
          "awayTeamId": "league-beltway-team-3",
          "homeScore": 0,
          "awayScore": 0,
          "completed": true
        },
        {
          "week": 3,
          "leagueId": "league-beltway",
          "homeTeamId": "league-beltway-team-4",
          "awayTeamId": "league-beltway-team-2",
          "homeScore": 0,
          "awayScore": 0,
          "completed": true
        },
        {
          "week": 3,
          "leagueId": "league-capitol",
          "homeTeamId": "league-capitol-team-1",
          "awayTeamId": "league-capitol-team-3",
          "homeScore": 0,
          "awayScore": 0,
          "completed": true
        },
        {
          "week": 3,
          "leagueId": "league-capitol",
          "homeTeamId": "league-capitol-team-4",
          "awayTeamId": "league-capitol-team-2",
          "homeScore": 0,
          "awayScore": 0,
          "completed": true
        },
        {
          "week": 3,
          "leagueId": "league-swamp",
          "homeTeamId": "league-swamp-team-1",
          "awayTeamId": "league-swamp-team-3",
          "homeScore": 0,
          "awayScore": 0,
          "completed": true
        },
        {
          "week": 3,
          "leagueId": "league-swamp",
          "homeTeamId": "league-swamp-team-4",
          "awayTeamId": "league-swamp-team-2",
          "homeScore": 0,
          "awayScore": 0,
          "completed": true
        }
      ]
    },
    {
      "week": 4,
      "matchups": [
        {
          "week": 4,
          "leagueId": "league-beltway",
          "homeTeamId": "league-beltway-team-1",
          "awayTeamId": "league-beltway-team-4",
          "homeScore": 24739,
          "awayScore": 3994,
          "completed": true
        },
        {
          "week": 4,
          "leagueId": "league-beltway",
          "homeTeamId": "league-beltway-team-2",
          "awayTeamId": "league-beltway-team-3",
          "homeScore": -5020,
          "awayScore": 1656,
          "completed": true
        },
        {
          "week": 4,
          "leagueId": "league-capitol",
          "homeTeamId": "league-capitol-team-1",
          "awayTeamId": "league-capitol-team-4",
          "homeScore": 24739,
          "awayScore": 3994,
          "completed": true
        },
        {
          "week": 4,
          "leagueId": "league-capitol",
          "homeTeamId": "league-capitol-team-2",
          "awayTeamId": "league-capitol-team-3",
          "homeScore": -5020,
          "awayScore": 1656,
          "completed": true
        },
        {
          "week": 4,
          "leagueId": "league-swamp",
          "homeTeamId": "league-swamp-team-1",
          "awayTeamId": "league-swamp-team-4",
          "homeScore": 24739,
          "awayScore": 3994,
          "completed": true
        },
        {
          "week": 4,
          "leagueId": "league-swamp",
          "homeTeamId": "league-swamp-team-2",
          "awayTeamId": "league-swamp-team-3",
          "homeScore": -5020,
          "awayScore": 1656,
          "completed": true
        }
      ]
    },
    {
      "week": 5,
      "matchups": [
        {
          "week": 5,
          "leagueId": "league-beltway",
          "homeTeamId": "league-beltway-team-1",
          "awayTeamId": "league-beltway-team-2",
          "homeScore": 6966,
          "awayScore": 35086,
          "completed": true
        },
        {
          "week": 5,
          "leagueId": "league-beltway",
          "homeTeamId": "league-beltway-team-3",
          "awayTeamId": "league-beltway-team-4",
          "homeScore": 17845,
          "awayScore": 24667.5,
          "completed": true
        },
        {
          "week": 5,
          "leagueId": "league-capitol",
          "homeTeamId": "league-capitol-team-1",
          "awayTeamId": "league-capitol-team-2",
          "homeScore": 6966,
          "awayScore": 35086,
          "completed": true
        },
        {
          "week": 5,
          "leagueId": "league-capitol",
          "homeTeamId": "league-capitol-team-3",
          "awayTeamId": "league-capitol-team-4",
          "homeScore": 17845,
          "awayScore": 24667.5,
          "completed": true
        },
        {
          "week": 5,
          "leagueId": "league-swamp",
          "homeTeamId": "league-swamp-team-1",
          "awayTeamId": "league-swamp-team-2",
          "homeScore": 6966,
          "awayScore": 35086,
          "completed": true
        },
        {
          "week": 5,
          "leagueId": "league-swamp",
          "homeTeamId": "league-swamp-team-3",
          "awayTeamId": "league-swamp-team-4",
          "homeScore": 17845,
          "awayScore": 24667.5,
          "completed": true
        }
      ]
    },
    {
      "week": 6,
      "matchups": [
        {
          "week": 6,
          "leagueId": "league-beltway",
          "homeTeamId": "league-beltway-team-1",
          "awayTeamId": "league-beltway-team-3",
          "homeScore": 7087,
          "awayScore": 11350,
          "completed": true
        },
        {
          "week": 6,
          "leagueId": "league-beltway",
          "homeTeamId": "league-beltway-team-4",
          "awayTeamId": "league-beltway-team-2",
          "homeScore": 0,
          "awayScore": 2858,
          "completed": true
        },
        {
          "week": 6,
          "leagueId": "league-capitol",
          "homeTeamId": "league-capitol-team-1",
          "awayTeamId": "league-capitol-team-3",
          "homeScore": 7087,
          "awayScore": 11350,
          "completed": true
        },
        {
          "week": 6,
          "leagueId": "league-capitol",
          "homeTeamId": "league-capitol-team-4",
          "awayTeamId": "league-capitol-team-2",
          "homeScore": 0,
          "awayScore": 2858,
          "completed": true
        },
        {
          "week": 6,
          "leagueId": "league-swamp",
          "homeTeamId": "league-swamp-team-1",
          "awayTeamId": "league-swamp-team-3",
          "homeScore": 7087,
          "awayScore": 11350,
          "completed": true
        },
        {
          "week": 6,
          "leagueId": "league-swamp",
          "homeTeamId": "league-swamp-team-4",
          "awayTeamId": "league-swamp-team-2",
          "homeScore": 0,
          "awayScore": 2858,
          "completed": true
        }
      ]
    }
  ],
  "weekResults": [
    {
      "week": 1,
      "teamId": "league-beltway-team-1",
      "points": 0,
      "politicianPoints": [
        {
          "bioguideId": "ALVA-JOHNBOOZMAN",
          "points": 0
        },
        {
          "bioguideId": "ALVA-THOMASSUOZZI",
          "points": 0
        },
        {
          "bioguideId": "C001047",
          "points": 0
        }
      ],
      "mvpBioguideId": "ALVA-JOHNBOOZMAN"
    },
    {
      "week": 1,
      "teamId": "league-beltway-team-2",
      "points": 0,
      "politicianPoints": [
        {
          "bioguideId": "ALVA-TONYWIED",
          "points": 0
        },
        {
          "bioguideId": "ALVA-JOSHGOTTHEIM",
          "points": 0
        },
        {
          "bioguideId": "K000375",
          "points": 0
        }
      ],
      "mvpBioguideId": "ALVA-TONYWIED"
    },
    {
      "week": 1,
      "teamId": "league-beltway-team-3",
      "points": 0,
      "politicianPoints": [
        {
          "bioguideId": "ALVA-JULIALETLOW",
          "points": 0
        },
        {
          "bioguideId": "ALVA-MARKWAYNEMUL",
          "points": 0
        },
        {
          "bioguideId": "ALVA-JOHNWHICKENL",
          "points": 0
        }
      ],
      "mvpBioguideId": "ALVA-JULIALETLOW"
    },
    {
      "week": 1,
      "teamId": "league-beltway-team-4",
      "points": 0,
      "politicianPoints": [
        {
          "bioguideId": "ALVA-RICHARDWALLE",
          "points": 0
        },
        {
          "bioguideId": "ALVA-JONATHANJACK",
          "points": 0
        },
        {
          "bioguideId": "ALVA-AUSTINSCOTT",
          "points": 0
        }
      ],
      "mvpBioguideId": "ALVA-RICHARDWALLE"
    },
    {
      "week": 2,
      "teamId": "league-beltway-team-1",
      "points": 0,
      "politicianPoints": [
        {
          "bioguideId": "ALVA-JOHNBOOZMAN",
          "points": 0
        },
        {
          "bioguideId": "ALVA-THOMASSUOZZI",
          "points": 0
        },
        {
          "bioguideId": "C001047",
          "points": 0
        }
      ],
      "mvpBioguideId": "ALVA-JOHNBOOZMAN"
    },
    {
      "week": 2,
      "teamId": "league-beltway-team-2",
      "points": 0,
      "politicianPoints": [
        {
          "bioguideId": "ALVA-TONYWIED",
          "points": 0
        },
        {
          "bioguideId": "ALVA-JOSHGOTTHEIM",
          "points": 0
        },
        {
          "bioguideId": "K000375",
          "points": 0
        }
      ],
      "mvpBioguideId": "ALVA-TONYWIED"
    },
    {
      "week": 2,
      "teamId": "league-beltway-team-3",
      "points": 0,
      "politicianPoints": [
        {
          "bioguideId": "ALVA-JULIALETLOW",
          "points": 0
        },
        {
          "bioguideId": "ALVA-MARKWAYNEMUL",
          "points": 0
        },
        {
          "bioguideId": "ALVA-JOHNWHICKENL",
          "points": 0
        }
      ],
      "mvpBioguideId": "ALVA-JULIALETLOW"
    },
    {
      "week": 2,
      "teamId": "league-beltway-team-4",
      "points": 0,
      "politicianPoints": [
        {
          "bioguideId": "ALVA-RICHARDWALLE",
          "points": 0
        },
        {
          "bioguideId": "ALVA-JONATHANJACK",
          "points": 0
        },
        {
          "bioguideId": "ALVA-AUSTINSCOTT",
          "points": 0
        }
      ],
      "mvpBioguideId": "ALVA-RICHARDWALLE"
    },
    {
      "week": 3,
      "teamId": "league-beltway-team-1",
      "points": 0,
      "politicianPoints": [
        {
          "bioguideId": "ALVA-JOHNBOOZMAN",
          "points": 0
        },
        {
          "bioguideId": "ALVA-THOMASSUOZZI",
          "points": 0
        },
        {
          "bioguideId": "C001047",
          "points": 0
        }
      ],
      "mvpBioguideId": "ALVA-JOHNBOOZMAN"
    },
    {
      "week": 3,
      "teamId": "league-beltway-team-2",
      "points": 0,
      "politicianPoints": [
        {
          "bioguideId": "ALVA-TONYWIED",
          "points": 0
        },
        {
          "bioguideId": "ALVA-JOSHGOTTHEIM",
          "points": 0
        },
        {
          "bioguideId": "K000375",
          "points": 0
        }
      ],
      "mvpBioguideId": "ALVA-TONYWIED"
    },
    {
      "week": 3,
      "teamId": "league-beltway-team-3",
      "points": 0,
      "politicianPoints": [
        {
          "bioguideId": "ALVA-JULIALETLOW",
          "points": 0
        },
        {
          "bioguideId": "ALVA-MARKWAYNEMUL",
          "points": 0
        },
        {
          "bioguideId": "ALVA-JOHNWHICKENL",
          "points": 0
        }
      ],
      "mvpBioguideId": "ALVA-JULIALETLOW"
    },
    {
      "week": 3,
      "teamId": "league-beltway-team-4",
      "points": 0,
      "politicianPoints": [
        {
          "bioguideId": "ALVA-RICHARDWALLE",
          "points": 0
        },
        {
          "bioguideId": "ALVA-JONATHANJACK",
          "points": 0
        },
        {
          "bioguideId": "ALVA-AUSTINSCOTT",
          "points": 0
        }
      ],
      "mvpBioguideId": "ALVA-RICHARDWALLE"
    },
    {
      "week": 4,
      "teamId": "league-beltway-team-1",
      "points": 24739,
      "politicianPoints": [
        {
          "bioguideId": "ALVA-JOHNBOOZMAN",
          "points": 25980
        },
        {
          "bioguideId": "ALVA-THOMASSUOZZI",
          "points": 0
        },
        {
          "bioguideId": "C001047",
          "points": -1241
        }
      ],
      "mvpBioguideId": "ALVA-JOHNBOOZMAN"
    },
    {
      "week": 4,
      "teamId": "league-beltway-team-2",
      "points": -5020,
      "politicianPoints": [
        {
          "bioguideId": "ALVA-TONYWIED",
          "points": -5020
        },
        {
          "bioguideId": "ALVA-JOSHGOTTHEIM",
          "points": 0
        },
        {
          "bioguideId": "K000375",
          "points": 0
        }
      ],
      "mvpBioguideId": "ALVA-JOSHGOTTHEIM"
    },
    {
      "week": 4,
      "teamId": "league-beltway-team-3",
      "points": 1656,
      "politicianPoints": [
        {
          "bioguideId": "ALVA-JULIALETLOW",
          "points": -1480
        },
        {
          "bioguideId": "ALVA-MARKWAYNEMUL",
          "points": 0
        },
        {
          "bioguideId": "ALVA-JOHNWHICKENL",
          "points": 3136
        }
      ],
      "mvpBioguideId": "ALVA-JOHNWHICKENL"
    },
    {
      "week": 4,
      "teamId": "league-beltway-team-4",
      "points": 3994,
      "politicianPoints": [
        {
          "bioguideId": "ALVA-RICHARDWALLE",
          "points": 0
        },
        {
          "bioguideId": "ALVA-JONATHANJACK",
          "points": 3994
        },
        {
          "bioguideId": "ALVA-AUSTINSCOTT",
          "points": 0
        }
      ],
      "mvpBioguideId": "ALVA-JONATHANJACK"
    },
    {
      "week": 5,
      "teamId": "league-beltway-team-1",
      "points": 6966,
      "politicianPoints": [
        {
          "bioguideId": "ALVA-JOHNBOOZMAN",
          "points": -581
        },
        {
          "bioguideId": "ALVA-THOMASSUOZZI",
          "points": 4291
        },
        {
          "bioguideId": "C001047",
          "points": 3256
        }
      ],
      "mvpBioguideId": "ALVA-THOMASSUOZZI"
    },
    {
      "week": 5,
      "teamId": "league-beltway-team-2",
      "points": 35086,
      "politicianPoints": [
        {
          "bioguideId": "ALVA-TONYWIED",
          "points": 28203
        },
        {
          "bioguideId": "ALVA-JOSHGOTTHEIM",
          "points": 3445
        },
        {
          "bioguideId": "K000375",
          "points": 3438
        }
      ],
      "mvpBioguideId": "ALVA-TONYWIED"
    },
    {
      "week": 5,
      "teamId": "league-beltway-team-3",
      "points": 17845,
      "politicianPoints": [
        {
          "bioguideId": "ALVA-JULIALETLOW",
          "points": 17845
        },
        {
          "bioguideId": "ALVA-MARKWAYNEMUL",
          "points": 0
        },
        {
          "bioguideId": "ALVA-JOHNWHICKENL",
          "points": 0
        }
      ],
      "mvpBioguideId": "ALVA-JULIALETLOW"
    },
    {
      "week": 5,
      "teamId": "league-beltway-team-4",
      "points": 24667.5,
      "politicianPoints": [
        {
          "bioguideId": "ALVA-RICHARDWALLE",
          "points": 18803.5
        },
        {
          "bioguideId": "ALVA-JONATHANJACK",
          "points": 3565
        },
        {
          "bioguideId": "ALVA-AUSTINSCOTT",
          "points": 2299
        }
      ],
      "mvpBioguideId": "ALVA-RICHARDWALLE"
    },
    {
      "week": 6,
      "teamId": "league-beltway-team-1",
      "points": 7087,
      "politicianPoints": [
        {
          "bioguideId": "ALVA-JOHNBOOZMAN",
          "points": 7087
        },
        {
          "bioguideId": "ALVA-THOMASSUOZZI",
          "points": 0
        },
        {
          "bioguideId": "C001047",
          "points": 0
        }
      ],
      "mvpBioguideId": "ALVA-JOHNBOOZMAN"
    },
    {
      "week": 6,
      "teamId": "league-beltway-team-2",
      "points": 2858,
      "politicianPoints": [
        {
          "bioguideId": "ALVA-TONYWIED",
          "points": 0
        },
        {
          "bioguideId": "ALVA-JOSHGOTTHEIM",
          "points": 2858
        },
        {
          "bioguideId": "K000375",
          "points": 0
        }
      ],
      "mvpBioguideId": "ALVA-JOSHGOTTHEIM"
    },
    {
      "week": 6,
      "teamId": "league-beltway-team-3",
      "points": 11350,
      "politicianPoints": [
        {
          "bioguideId": "ALVA-JULIALETLOW",
          "points": 0
        },
        {
          "bioguideId": "ALVA-MARKWAYNEMUL",
          "points": 11350
        },
        {
          "bioguideId": "ALVA-JOHNWHICKENL",
          "points": 0
        }
      ],
      "mvpBioguideId": "ALVA-MARKWAYNEMUL"
    },
    {
      "week": 6,
      "teamId": "league-beltway-team-4",
      "points": 0,
      "politicianPoints": [
        {
          "bioguideId": "ALVA-RICHARDWALLE",
          "points": 0
        },
        {
          "bioguideId": "ALVA-JONATHANJACK",
          "points": 0
        },
        {
          "bioguideId": "ALVA-AUSTINSCOTT",
          "points": 0
        }
      ],
      "mvpBioguideId": "ALVA-RICHARDWALLE"
    },
    {
      "week": 1,
      "teamId": "league-capitol-team-1",
      "points": 0,
      "politicianPoints": [
        {
          "bioguideId": "ALVA-JOHNBOOZMAN",
          "points": 0
        },
        {
          "bioguideId": "ALVA-THOMASSUOZZI",
          "points": 0
        },
        {
          "bioguideId": "C001047",
          "points": 0
        }
      ],
      "mvpBioguideId": "ALVA-JOHNBOOZMAN"
    },
    {
      "week": 1,
      "teamId": "league-capitol-team-2",
      "points": 0,
      "politicianPoints": [
        {
          "bioguideId": "ALVA-TONYWIED",
          "points": 0
        },
        {
          "bioguideId": "ALVA-JOSHGOTTHEIM",
          "points": 0
        },
        {
          "bioguideId": "K000375",
          "points": 0
        }
      ],
      "mvpBioguideId": "ALVA-TONYWIED"
    },
    {
      "week": 1,
      "teamId": "league-capitol-team-3",
      "points": 0,
      "politicianPoints": [
        {
          "bioguideId": "ALVA-JULIALETLOW",
          "points": 0
        },
        {
          "bioguideId": "ALVA-MARKWAYNEMUL",
          "points": 0
        },
        {
          "bioguideId": "ALVA-JOHNWHICKENL",
          "points": 0
        }
      ],
      "mvpBioguideId": "ALVA-JULIALETLOW"
    },
    {
      "week": 1,
      "teamId": "league-capitol-team-4",
      "points": 0,
      "politicianPoints": [
        {
          "bioguideId": "ALVA-RICHARDWALLE",
          "points": 0
        },
        {
          "bioguideId": "ALVA-JONATHANJACK",
          "points": 0
        },
        {
          "bioguideId": "ALVA-AUSTINSCOTT",
          "points": 0
        }
      ],
      "mvpBioguideId": "ALVA-RICHARDWALLE"
    },
    {
      "week": 2,
      "teamId": "league-capitol-team-1",
      "points": 0,
      "politicianPoints": [
        {
          "bioguideId": "ALVA-JOHNBOOZMAN",
          "points": 0
        },
        {
          "bioguideId": "ALVA-THOMASSUOZZI",
          "points": 0
        },
        {
          "bioguideId": "C001047",
          "points": 0
        }
      ],
      "mvpBioguideId": "ALVA-JOHNBOOZMAN"
    },
    {
      "week": 2,
      "teamId": "league-capitol-team-2",
      "points": 0,
      "politicianPoints": [
        {
          "bioguideId": "ALVA-TONYWIED",
          "points": 0
        },
        {
          "bioguideId": "ALVA-JOSHGOTTHEIM",
          "points": 0
        },
        {
          "bioguideId": "K000375",
          "points": 0
        }
      ],
      "mvpBioguideId": "ALVA-TONYWIED"
    },
    {
      "week": 2,
      "teamId": "league-capitol-team-3",
      "points": 0,
      "politicianPoints": [
        {
          "bioguideId": "ALVA-JULIALETLOW",
          "points": 0
        },
        {
          "bioguideId": "ALVA-MARKWAYNEMUL",
          "points": 0
        },
        {
          "bioguideId": "ALVA-JOHNWHICKENL",
          "points": 0
        }
      ],
      "mvpBioguideId": "ALVA-JULIALETLOW"
    },
    {
      "week": 2,
      "teamId": "league-capitol-team-4",
      "points": 0,
      "politicianPoints": [
        {
          "bioguideId": "ALVA-RICHARDWALLE",
          "points": 0
        },
        {
          "bioguideId": "ALVA-JONATHANJACK",
          "points": 0
        },
        {
          "bioguideId": "ALVA-AUSTINSCOTT",
          "points": 0
        }
      ],
      "mvpBioguideId": "ALVA-RICHARDWALLE"
    },
    {
      "week": 3,
      "teamId": "league-capitol-team-1",
      "points": 0,
      "politicianPoints": [
        {
          "bioguideId": "ALVA-JOHNBOOZMAN",
          "points": 0
        },
        {
          "bioguideId": "ALVA-THOMASSUOZZI",
          "points": 0
        },
        {
          "bioguideId": "C001047",
          "points": 0
        }
      ],
      "mvpBioguideId": "ALVA-JOHNBOOZMAN"
    },
    {
      "week": 3,
      "teamId": "league-capitol-team-2",
      "points": 0,
      "politicianPoints": [
        {
          "bioguideId": "ALVA-TONYWIED",
          "points": 0
        },
        {
          "bioguideId": "ALVA-JOSHGOTTHEIM",
          "points": 0
        },
        {
          "bioguideId": "K000375",
          "points": 0
        }
      ],
      "mvpBioguideId": "ALVA-TONYWIED"
    },
    {
      "week": 3,
      "teamId": "league-capitol-team-3",
      "points": 0,
      "politicianPoints": [
        {
          "bioguideId": "ALVA-JULIALETLOW",
          "points": 0
        },
        {
          "bioguideId": "ALVA-MARKWAYNEMUL",
          "points": 0
        },
        {
          "bioguideId": "ALVA-JOHNWHICKENL",
          "points": 0
        }
      ],
      "mvpBioguideId": "ALVA-JULIALETLOW"
    },
    {
      "week": 3,
      "teamId": "league-capitol-team-4",
      "points": 0,
      "politicianPoints": [
        {
          "bioguideId": "ALVA-RICHARDWALLE",
          "points": 0
        },
        {
          "bioguideId": "ALVA-JONATHANJACK",
          "points": 0
        },
        {
          "bioguideId": "ALVA-AUSTINSCOTT",
          "points": 0
        }
      ],
      "mvpBioguideId": "ALVA-RICHARDWALLE"
    },
    {
      "week": 4,
      "teamId": "league-capitol-team-1",
      "points": 24739,
      "politicianPoints": [
        {
          "bioguideId": "ALVA-JOHNBOOZMAN",
          "points": 25980
        },
        {
          "bioguideId": "ALVA-THOMASSUOZZI",
          "points": 0
        },
        {
          "bioguideId": "C001047",
          "points": -1241
        }
      ],
      "mvpBioguideId": "ALVA-JOHNBOOZMAN"
    },
    {
      "week": 4,
      "teamId": "league-capitol-team-2",
      "points": -5020,
      "politicianPoints": [
        {
          "bioguideId": "ALVA-TONYWIED",
          "points": -5020
        },
        {
          "bioguideId": "ALVA-JOSHGOTTHEIM",
          "points": 0
        },
        {
          "bioguideId": "K000375",
          "points": 0
        }
      ],
      "mvpBioguideId": "ALVA-JOSHGOTTHEIM"
    },
    {
      "week": 4,
      "teamId": "league-capitol-team-3",
      "points": 1656,
      "politicianPoints": [
        {
          "bioguideId": "ALVA-JULIALETLOW",
          "points": -1480
        },
        {
          "bioguideId": "ALVA-MARKWAYNEMUL",
          "points": 0
        },
        {
          "bioguideId": "ALVA-JOHNWHICKENL",
          "points": 3136
        }
      ],
      "mvpBioguideId": "ALVA-JOHNWHICKENL"
    },
    {
      "week": 4,
      "teamId": "league-capitol-team-4",
      "points": 3994,
      "politicianPoints": [
        {
          "bioguideId": "ALVA-RICHARDWALLE",
          "points": 0
        },
        {
          "bioguideId": "ALVA-JONATHANJACK",
          "points": 3994
        },
        {
          "bioguideId": "ALVA-AUSTINSCOTT",
          "points": 0
        }
      ],
      "mvpBioguideId": "ALVA-JONATHANJACK"
    },
    {
      "week": 5,
      "teamId": "league-capitol-team-1",
      "points": 6966,
      "politicianPoints": [
        {
          "bioguideId": "ALVA-JOHNBOOZMAN",
          "points": -581
        },
        {
          "bioguideId": "ALVA-THOMASSUOZZI",
          "points": 4291
        },
        {
          "bioguideId": "C001047",
          "points": 3256
        }
      ],
      "mvpBioguideId": "ALVA-THOMASSUOZZI"
    },
    {
      "week": 5,
      "teamId": "league-capitol-team-2",
      "points": 35086,
      "politicianPoints": [
        {
          "bioguideId": "ALVA-TONYWIED",
          "points": 28203
        },
        {
          "bioguideId": "ALVA-JOSHGOTTHEIM",
          "points": 3445
        },
        {
          "bioguideId": "K000375",
          "points": 3438
        }
      ],
      "mvpBioguideId": "ALVA-TONYWIED"
    },
    {
      "week": 5,
      "teamId": "league-capitol-team-3",
      "points": 17845,
      "politicianPoints": [
        {
          "bioguideId": "ALVA-JULIALETLOW",
          "points": 17845
        },
        {
          "bioguideId": "ALVA-MARKWAYNEMUL",
          "points": 0
        },
        {
          "bioguideId": "ALVA-JOHNWHICKENL",
          "points": 0
        }
      ],
      "mvpBioguideId": "ALVA-JULIALETLOW"
    },
    {
      "week": 5,
      "teamId": "league-capitol-team-4",
      "points": 24667.5,
      "politicianPoints": [
        {
          "bioguideId": "ALVA-RICHARDWALLE",
          "points": 18803.5
        },
        {
          "bioguideId": "ALVA-JONATHANJACK",
          "points": 3565
        },
        {
          "bioguideId": "ALVA-AUSTINSCOTT",
          "points": 2299
        }
      ],
      "mvpBioguideId": "ALVA-RICHARDWALLE"
    },
    {
      "week": 6,
      "teamId": "league-capitol-team-1",
      "points": 7087,
      "politicianPoints": [
        {
          "bioguideId": "ALVA-JOHNBOOZMAN",
          "points": 7087
        },
        {
          "bioguideId": "ALVA-THOMASSUOZZI",
          "points": 0
        },
        {
          "bioguideId": "C001047",
          "points": 0
        }
      ],
      "mvpBioguideId": "ALVA-JOHNBOOZMAN"
    },
    {
      "week": 6,
      "teamId": "league-capitol-team-2",
      "points": 2858,
      "politicianPoints": [
        {
          "bioguideId": "ALVA-TONYWIED",
          "points": 0
        },
        {
          "bioguideId": "ALVA-JOSHGOTTHEIM",
          "points": 2858
        },
        {
          "bioguideId": "K000375",
          "points": 0
        }
      ],
      "mvpBioguideId": "ALVA-JOSHGOTTHEIM"
    },
    {
      "week": 6,
      "teamId": "league-capitol-team-3",
      "points": 11350,
      "politicianPoints": [
        {
          "bioguideId": "ALVA-JULIALETLOW",
          "points": 0
        },
        {
          "bioguideId": "ALVA-MARKWAYNEMUL",
          "points": 11350
        },
        {
          "bioguideId": "ALVA-JOHNWHICKENL",
          "points": 0
        }
      ],
      "mvpBioguideId": "ALVA-MARKWAYNEMUL"
    },
    {
      "week": 6,
      "teamId": "league-capitol-team-4",
      "points": 0,
      "politicianPoints": [
        {
          "bioguideId": "ALVA-RICHARDWALLE",
          "points": 0
        },
        {
          "bioguideId": "ALVA-JONATHANJACK",
          "points": 0
        },
        {
          "bioguideId": "ALVA-AUSTINSCOTT",
          "points": 0
        }
      ],
      "mvpBioguideId": "ALVA-RICHARDWALLE"
    },
    {
      "week": 1,
      "teamId": "league-swamp-team-1",
      "points": 0,
      "politicianPoints": [
        {
          "bioguideId": "ALVA-JOHNBOOZMAN",
          "points": 0
        },
        {
          "bioguideId": "ALVA-THOMASSUOZZI",
          "points": 0
        },
        {
          "bioguideId": "C001047",
          "points": 0
        }
      ],
      "mvpBioguideId": "ALVA-JOHNBOOZMAN"
    },
    {
      "week": 1,
      "teamId": "league-swamp-team-2",
      "points": 0,
      "politicianPoints": [
        {
          "bioguideId": "ALVA-TONYWIED",
          "points": 0
        },
        {
          "bioguideId": "ALVA-JOSHGOTTHEIM",
          "points": 0
        },
        {
          "bioguideId": "K000375",
          "points": 0
        }
      ],
      "mvpBioguideId": "ALVA-TONYWIED"
    },
    {
      "week": 1,
      "teamId": "league-swamp-team-3",
      "points": 0,
      "politicianPoints": [
        {
          "bioguideId": "ALVA-JULIALETLOW",
          "points": 0
        },
        {
          "bioguideId": "ALVA-MARKWAYNEMUL",
          "points": 0
        },
        {
          "bioguideId": "ALVA-JOHNWHICKENL",
          "points": 0
        }
      ],
      "mvpBioguideId": "ALVA-JULIALETLOW"
    },
    {
      "week": 1,
      "teamId": "league-swamp-team-4",
      "points": 0,
      "politicianPoints": [
        {
          "bioguideId": "ALVA-RICHARDWALLE",
          "points": 0
        },
        {
          "bioguideId": "ALVA-JONATHANJACK",
          "points": 0
        },
        {
          "bioguideId": "ALVA-AUSTINSCOTT",
          "points": 0
        }
      ],
      "mvpBioguideId": "ALVA-RICHARDWALLE"
    },
    {
      "week": 2,
      "teamId": "league-swamp-team-1",
      "points": 0,
      "politicianPoints": [
        {
          "bioguideId": "ALVA-JOHNBOOZMAN",
          "points": 0
        },
        {
          "bioguideId": "ALVA-THOMASSUOZZI",
          "points": 0
        },
        {
          "bioguideId": "C001047",
          "points": 0
        }
      ],
      "mvpBioguideId": "ALVA-JOHNBOOZMAN"
    },
    {
      "week": 2,
      "teamId": "league-swamp-team-2",
      "points": 0,
      "politicianPoints": [
        {
          "bioguideId": "ALVA-TONYWIED",
          "points": 0
        },
        {
          "bioguideId": "ALVA-JOSHGOTTHEIM",
          "points": 0
        },
        {
          "bioguideId": "K000375",
          "points": 0
        }
      ],
      "mvpBioguideId": "ALVA-TONYWIED"
    },
    {
      "week": 2,
      "teamId": "league-swamp-team-3",
      "points": 0,
      "politicianPoints": [
        {
          "bioguideId": "ALVA-JULIALETLOW",
          "points": 0
        },
        {
          "bioguideId": "ALVA-MARKWAYNEMUL",
          "points": 0
        },
        {
          "bioguideId": "ALVA-JOHNWHICKENL",
          "points": 0
        }
      ],
      "mvpBioguideId": "ALVA-JULIALETLOW"
    },
    {
      "week": 2,
      "teamId": "league-swamp-team-4",
      "points": 0,
      "politicianPoints": [
        {
          "bioguideId": "ALVA-RICHARDWALLE",
          "points": 0
        },
        {
          "bioguideId": "ALVA-JONATHANJACK",
          "points": 0
        },
        {
          "bioguideId": "ALVA-AUSTINSCOTT",
          "points": 0
        }
      ],
      "mvpBioguideId": "ALVA-RICHARDWALLE"
    },
    {
      "week": 3,
      "teamId": "league-swamp-team-1",
      "points": 0,
      "politicianPoints": [
        {
          "bioguideId": "ALVA-JOHNBOOZMAN",
          "points": 0
        },
        {
          "bioguideId": "ALVA-THOMASSUOZZI",
          "points": 0
        },
        {
          "bioguideId": "C001047",
          "points": 0
        }
      ],
      "mvpBioguideId": "ALVA-JOHNBOOZMAN"
    },
    {
      "week": 3,
      "teamId": "league-swamp-team-2",
      "points": 0,
      "politicianPoints": [
        {
          "bioguideId": "ALVA-TONYWIED",
          "points": 0
        },
        {
          "bioguideId": "ALVA-JOSHGOTTHEIM",
          "points": 0
        },
        {
          "bioguideId": "K000375",
          "points": 0
        }
      ],
      "mvpBioguideId": "ALVA-TONYWIED"
    },
    {
      "week": 3,
      "teamId": "league-swamp-team-3",
      "points": 0,
      "politicianPoints": [
        {
          "bioguideId": "ALVA-JULIALETLOW",
          "points": 0
        },
        {
          "bioguideId": "ALVA-MARKWAYNEMUL",
          "points": 0
        },
        {
          "bioguideId": "ALVA-JOHNWHICKENL",
          "points": 0
        }
      ],
      "mvpBioguideId": "ALVA-JULIALETLOW"
    },
    {
      "week": 3,
      "teamId": "league-swamp-team-4",
      "points": 0,
      "politicianPoints": [
        {
          "bioguideId": "ALVA-RICHARDWALLE",
          "points": 0
        },
        {
          "bioguideId": "ALVA-JONATHANJACK",
          "points": 0
        },
        {
          "bioguideId": "ALVA-AUSTINSCOTT",
          "points": 0
        }
      ],
      "mvpBioguideId": "ALVA-RICHARDWALLE"
    },
    {
      "week": 4,
      "teamId": "league-swamp-team-1",
      "points": 24739,
      "politicianPoints": [
        {
          "bioguideId": "ALVA-JOHNBOOZMAN",
          "points": 25980
        },
        {
          "bioguideId": "ALVA-THOMASSUOZZI",
          "points": 0
        },
        {
          "bioguideId": "C001047",
          "points": -1241
        }
      ],
      "mvpBioguideId": "ALVA-JOHNBOOZMAN"
    },
    {
      "week": 4,
      "teamId": "league-swamp-team-2",
      "points": -5020,
      "politicianPoints": [
        {
          "bioguideId": "ALVA-TONYWIED",
          "points": -5020
        },
        {
          "bioguideId": "ALVA-JOSHGOTTHEIM",
          "points": 0
        },
        {
          "bioguideId": "K000375",
          "points": 0
        }
      ],
      "mvpBioguideId": "ALVA-JOSHGOTTHEIM"
    },
    {
      "week": 4,
      "teamId": "league-swamp-team-3",
      "points": 1656,
      "politicianPoints": [
        {
          "bioguideId": "ALVA-JULIALETLOW",
          "points": -1480
        },
        {
          "bioguideId": "ALVA-MARKWAYNEMUL",
          "points": 0
        },
        {
          "bioguideId": "ALVA-JOHNWHICKENL",
          "points": 3136
        }
      ],
      "mvpBioguideId": "ALVA-JOHNWHICKENL"
    },
    {
      "week": 4,
      "teamId": "league-swamp-team-4",
      "points": 3994,
      "politicianPoints": [
        {
          "bioguideId": "ALVA-RICHARDWALLE",
          "points": 0
        },
        {
          "bioguideId": "ALVA-JONATHANJACK",
          "points": 3994
        },
        {
          "bioguideId": "ALVA-AUSTINSCOTT",
          "points": 0
        }
      ],
      "mvpBioguideId": "ALVA-JONATHANJACK"
    },
    {
      "week": 5,
      "teamId": "league-swamp-team-1",
      "points": 6966,
      "politicianPoints": [
        {
          "bioguideId": "ALVA-JOHNBOOZMAN",
          "points": -581
        },
        {
          "bioguideId": "ALVA-THOMASSUOZZI",
          "points": 4291
        },
        {
          "bioguideId": "C001047",
          "points": 3256
        }
      ],
      "mvpBioguideId": "ALVA-THOMASSUOZZI"
    },
    {
      "week": 5,
      "teamId": "league-swamp-team-2",
      "points": 35086,
      "politicianPoints": [
        {
          "bioguideId": "ALVA-TONYWIED",
          "points": 28203
        },
        {
          "bioguideId": "ALVA-JOSHGOTTHEIM",
          "points": 3445
        },
        {
          "bioguideId": "K000375",
          "points": 3438
        }
      ],
      "mvpBioguideId": "ALVA-TONYWIED"
    },
    {
      "week": 5,
      "teamId": "league-swamp-team-3",
      "points": 17845,
      "politicianPoints": [
        {
          "bioguideId": "ALVA-JULIALETLOW",
          "points": 17845
        },
        {
          "bioguideId": "ALVA-MARKWAYNEMUL",
          "points": 0
        },
        {
          "bioguideId": "ALVA-JOHNWHICKENL",
          "points": 0
        }
      ],
      "mvpBioguideId": "ALVA-JULIALETLOW"
    },
    {
      "week": 5,
      "teamId": "league-swamp-team-4",
      "points": 24667.5,
      "politicianPoints": [
        {
          "bioguideId": "ALVA-RICHARDWALLE",
          "points": 18803.5
        },
        {
          "bioguideId": "ALVA-JONATHANJACK",
          "points": 3565
        },
        {
          "bioguideId": "ALVA-AUSTINSCOTT",
          "points": 2299
        }
      ],
      "mvpBioguideId": "ALVA-RICHARDWALLE"
    },
    {
      "week": 6,
      "teamId": "league-swamp-team-1",
      "points": 7087,
      "politicianPoints": [
        {
          "bioguideId": "ALVA-JOHNBOOZMAN",
          "points": 7087
        },
        {
          "bioguideId": "ALVA-THOMASSUOZZI",
          "points": 0
        },
        {
          "bioguideId": "C001047",
          "points": 0
        }
      ],
      "mvpBioguideId": "ALVA-JOHNBOOZMAN"
    },
    {
      "week": 6,
      "teamId": "league-swamp-team-2",
      "points": 2858,
      "politicianPoints": [
        {
          "bioguideId": "ALVA-TONYWIED",
          "points": 0
        },
        {
          "bioguideId": "ALVA-JOSHGOTTHEIM",
          "points": 2858
        },
        {
          "bioguideId": "K000375",
          "points": 0
        }
      ],
      "mvpBioguideId": "ALVA-JOSHGOTTHEIM"
    },
    {
      "week": 6,
      "teamId": "league-swamp-team-3",
      "points": 11350,
      "politicianPoints": [
        {
          "bioguideId": "ALVA-JULIALETLOW",
          "points": 0
        },
        {
          "bioguideId": "ALVA-MARKWAYNEMUL",
          "points": 11350
        },
        {
          "bioguideId": "ALVA-JOHNWHICKENL",
          "points": 0
        }
      ],
      "mvpBioguideId": "ALVA-MARKWAYNEMUL"
    },
    {
      "week": 6,
      "teamId": "league-swamp-team-4",
      "points": 0,
      "politicianPoints": [
        {
          "bioguideId": "ALVA-RICHARDWALLE",
          "points": 0
        },
        {
          "bioguideId": "ALVA-JONATHANJACK",
          "points": 0
        },
        {
          "bioguideId": "ALVA-AUSTINSCOTT",
          "points": 0
        }
      ],
      "mvpBioguideId": "ALVA-RICHARDWALLE"
    }
  ]
}